sos_r/__init__.py
sos_r/_version.py
sos_r/kernel.py
sos_r-0.20.1.dist-info/LICENSE
sos_r-0.20.1.dist-info/METADATA
sos_r-0.20.1.dist-info/WHEEL
sos_r-0.20.1.dist-info/entry_points.txt
sos_r-0.20.1.dist-info/top_level.txt
sos_r-0.20.1.dist-info/RECORD
