Metadata-Version: 2.1
Name: sos-r
Version: 0.20.1
Summary: SoS Notebook extension for language R
Home-page: https://github.com/vatlab/SOS
Author: Bo Peng
Author-email: Bo.Peng@bcm.edu
Maintainer: Bo Peng
Maintainer-email: Bo.Peng@bcm.edu
License: 3-clause BSD
Platform: UNKNOWN
Classifier: Development Status :: 4 - Beta
Classifier: Environment :: Console
Classifier: License :: OSI Approved :: BSD License
Classifier: Natural Language :: English
Classifier: Operating System :: POSIX :: Linux
Classifier: Operating System :: MacOS :: MacOS X
Classifier: Operating System :: Microsoft :: Windows
Classifier: Intended Audience :: Information Technology
Classifier: Intended Audience :: Science/Research
Classifier: Programming Language :: Python :: 3 :: Only
Classifier: Programming Language :: Python :: Implementation :: CPython
Requires-Dist: sos (>=0.19.8)
Requires-Dist: sos-notebook (>=0.24.0)
Requires-Dist: pyarrow (>=0.13.1)
Requires-Dist: pandas
Requires-Dist: numpy
